globalmart_api/__init__.py
globalmart_api/oops.py
get_datafrom_api-0.1.dist-info/METADATA
get_datafrom_api-0.1.dist-info/WHEEL
get_datafrom_api-0.1.dist-info/top_level.txt
get_datafrom_api-0.1.dist-info/RECORD
